AUTHORS
LICENSE
MANIFEST.in
NEWS
README
setup.py
doc/html/.buildinfo
doc/html/api.html
doc/html/embed.html
doc/html/genindex.html
doc/html/handbook.html
doc/html/index.html
doc/html/objects.inv
doc/html/overview.html
doc/html/py-modindex.html
doc/html/search.html
doc/html/searchindex.js
doc/html/tutorial.html
doc/html/_images/administrative-directory-schema.png
doc/html/_images/administrative-directory-small-schema.png
doc/html/_images/htsql-web-service.png
doc/html/_images/local-scopes.png
doc/html/_images/model-and-instance.png
doc/html/_images/quotient-class.png
doc/html/_images/sample-instance-1.png
doc/html/_images/sample-instance-2.png
doc/html/_images/sample-model.png
doc/html/_images/show_school.png
doc/html/_images/singular-links.png
doc/html/_images/total-links.png
doc/html/_images/unique-links.png
doc/html/_sources/api.txt
doc/html/_sources/embed.txt
doc/html/_sources/handbook.txt
doc/html/_sources/index.txt
doc/html/_sources/overview.txt
doc/html/_sources/tutorial.txt
doc/html/_sources/admin/cloud.txt
doc/html/_sources/admin/deploy.txt
doc/html/_sources/admin/index.txt
doc/html/_sources/admin/install.txt
doc/html/_sources/admin/usage.txt
doc/html/_sources/man/htsql-ctl.1.txt
doc/html/_sources/man/index.txt
doc/html/_sources/ref/flows.txt
doc/html/_sources/ref/functions.txt
doc/html/_sources/ref/index.txt
doc/html/_sources/ref/model.txt
doc/html/_sources/ref/scopes.txt
doc/html/_sources/ref/syntax.txt
doc/html/_sources/ref/types.txt
doc/html/_static/basic.css
doc/html/_static/default.css
doc/html/_static/doctools.js
doc/html/_static/file.png
doc/html/_static/htsqldoc.css
doc/html/_static/jquery.js
doc/html/_static/minus.png
doc/html/_static/plus.png
doc/html/_static/pygments.css
doc/html/_static/searchtools.js
doc/html/_static/sidebar.js
doc/html/_static/underscore.js
doc/html/admin/cloud.html
doc/html/admin/deploy.html
doc/html/admin/index.html
doc/html/admin/install.html
doc/html/admin/usage.html
doc/html/man/htsql-ctl.1.html
doc/html/man/index.html
src/HTSQL.egg-info/PKG-INFO
src/HTSQL.egg-info/SOURCES.txt
src/HTSQL.egg-info/dependency_links.txt
src/HTSQL.egg-info/entry_points.txt
src/HTSQL.egg-info/not-zip-safe
src/HTSQL.egg-info/requires.txt
src/HTSQL.egg-info/top_level.txt
