Metadata-Version: 1.0
Name: HTSQL
Version: 2.3.3
Summary: A Database Query Language (core & SQLite backend)
Home-page: http://htsql.org/
Author: Clark C. Evans and Kirill Simonov; Prometheus Research, LLC
Author-email: cce@clarkevans.com, xi@resolvent.net
License: AGPLv3 or Permissive for use with Open Source databases
Keywords: sql relational database query language
Platform: Any
Classifier: Development Status :: 4 - Beta
Classifier: Environment :: Console
Classifier: Environment :: Web Environment
Classifier: Intended Audience :: Developers
Classifier: Intended Audience :: Information Technology
Classifier: Intended Audience :: Science/Research
Classifier: License :: OSI Approved :: GNU Affero General Public License v3
Classifier: License :: Free To Use But Restricted
Classifier: License :: Other/Proprietary License
Classifier: Programming Language :: Python
Classifier: Programming Language :: Python :: 2.6
Classifier: Programming Language :: Python :: 2.7
Classifier: Programming Language :: SQL
Classifier: Topic :: Database :: Front-Ends
Classifier: Topic :: Internet :: WWW/HTTP :: WSGI
Classifier: Topic :: Software Development :: Libraries
